compiledb/__init__.py
compiledb/__main__.py
compiledb/__version__.py
compiledb/cli.py
compiledb/compiler.py
compiledb/parser.py
compiledb/utils.py
compiledb/commands/__init__.py
compiledb/commands/make.py
compiledb_plus-1.0.0.dist-info/LICENSE
compiledb_plus-1.0.0.dist-info/METADATA
compiledb_plus-1.0.0.dist-info/WHEEL
compiledb_plus-1.0.0.dist-info/entry_points.txt
compiledb_plus-1.0.0.dist-info/top_level.txt
compiledb_plus-1.0.0.dist-info/RECORD
