Metadata-Version: 2.1
Name: compiledb-plus
Version: 1.0.0
Summary: Tool for generating Clang JSON Compilation Database files for make-based build systems. A fork of https://github.com/nickdiego/compiledb
Home-page: https://github.com/maxnilz/compiledb-plus
Author: maxnilz
Author-email: maxnilz@gmail.com
License: GPLv3
Project-URL: Issue Tracking, https://github.com/maxnilz/compiledb/issues
Keywords: compilation-database clang c cpp makefile rtags completion
Classifier: Development Status :: 5 - Production/Stable
Classifier: Intended Audience :: Developers
Classifier: Topic :: Software Development :: Build Tools
Classifier: License :: OSI Approved :: GNU General Public License v3 (GPLv3)
Classifier: Programming Language :: Python :: 2
Classifier: Programming Language :: Python :: 2.7
Classifier: Programming Language :: Python :: 3
Classifier: Programming Language :: Python :: 3.6
Classifier: Operating System :: OS Independent
Requires-Python: >=2.7,!=3.0.*,!=3.1.*,!=3.2.*,!=3.3.*,!=3.4.*,!=3.5.*
License-File: LICENSE
Requires-Dist: click
Requires-Dist: bashlex
Requires-Dist: shutilwhich
Provides-Extra: dev
Provides-Extra: test
Requires-Dist: pytest ; extra == 'test'
